Metadata-Version: 1.1
Name: PyDejavu
Version: 0.1
Summary: Dejavu Audio Fingerprinting
Home-page: http://github.com/tuxdna/dejavu
Author: worldveil
Author-email: will.drevo@gmail.com
License: Apache 2.0
Platform: Any
Classifier: Development Status :: 4 - Beta
Classifier: Environment :: Console
Classifier: Intended Audience :: Developers
Classifier: License :: OSI Approved :: Apache Software License
Classifier: Operating System :: OS Independent
Classifier: Topic :: Software Development :: Libraries :: Python Modules
